{
    "nodes":[
        {
            "pid":"377300199901150512",
            "phone":"12345678901",
            "name":"张三",
            "gender":"男",
            "diagnosedTime":"2021-11-13",
            "level":1,
            "type":"确诊"
        },
        {
            "pid":"377300199901150513",
            "phone":"12345678902",
            "name":"李四",
            "gender":"女",
            "diagnosedTime":"2021-11-16",
            "level":0,
            "type":"确诊"
        },
        {
            "pid":"377300199901150518",
            "phone":"12345678903",
            "name":"王五",
            "gender":"男",
            "diagnosedTime":"2021-11-13",
            "level":2,
            "type":"无症状感染"
        }
    ],
    "edges":[
        {
            "id":0,
            "source":1,
            "target":0,
            "relation":"夫妻同居感染",
            "isTruth":1
        },
        {
            "id":1,
            "source":0,
            "target":2,
            "relation":"同事感染",
            "isTruth":0
        }
    ]
}